smart_range/__init__.py
smart_range/exceptions.py
smart_range/smart_range.py
smart_range-1.1.1.dist-info/LICENSE
smart_range-1.1.1.dist-info/METADATA
smart_range-1.1.1.dist-info/WHEEL
smart_range-1.1.1.dist-info/top_level.txt
smart_range-1.1.1.dist-info/RECORD
