Metadata-Version: 2.1
Name: smart-range
Version: 1.1.1
Summary: A class to easily deal with ranges.
Home-page: https://github.com/PythonCoderAS/SmartRange
Author: PythonCoderAS
Author-email: sarkaraoyan@gmail.com
License: MIT
Platform: UNKNOWN
Requires-Python: >=3.6
License-File: LICENSE
Provides-Extra: docs
Requires-Dist: sphinx ; extra == 'docs'
